copy_git_repo
