Metadata-Version: 1.1
Name: copy-git-repo
Version: 0.1.2
Summary: Copy repo excluding files mentionned in .gitignore
Home-page: https://github.com/oscar6echo/copy-git-repo
Author: oscar6echo
Author-email: olivier.borderies@gmail.com
License: MIT
Download-URL: https://github.com/oscar6echo/copy-git-repo/tarball/0.1.2
Keywords: copy,git,repo,shutil
Platform: UNKNOWN
Classifier: Development Status :: 4 - Beta
Classifier: License :: OSI Approved :: MIT License
Classifier: Programming Language :: Python :: 3.5
Classifier: Programming Language :: Python :: 3.6
